odditylib/__init__.py
odditylib/collections.py
odditylib/decomp.py
odditylib/detector.py
odditylib/oddity.cpython-36m-darwin.so
oddity-0.1.0.dist-info/METADATA
oddity-0.1.0.dist-info/WHEEL
oddity-0.1.0.dist-info/top_level.txt
oddity-0.1.0.dist-info/RECORD
