Metadata-Version: 2.1
Name: oddity
Version: 0.1.0
Summary: Time Series Anomaly Detection
Home-page: https://github.com/Lleyton-Ariton/oddity
Author: Lleyton Ariton
Author-email: lleyton.ariton@egmail.com
License: UNKNOWN
Platform: UNKNOWN
Classifier: Programming Language :: Python :: 3
Classifier: Programming Language :: Rust
Classifier: Operating System :: OS Independent
Requires-Dist: numpy
